oddysey/__init__.py
oddysey-0.1.0.dist-info/LICENSE
oddysey-0.1.0.dist-info/WHEEL
oddysey-0.1.0.dist-info/METADATA
oddysey-0.1.0.dist-info/RECORD
