Metadata-Version: 2.1
Name: oddysey
Version: 0.1.0
Summary: A yet unknown accompanying project for iliad
Home-page: https://github.com/eganjs/oddysey
License: MIT
Author: Joseph Egan
Author-email: joseph.s.egan@gmail.com
Requires-Python: >=3.6,<4.0
Classifier: License :: OSI Approved :: MIT License
Classifier: Programming Language :: Python :: 3
Classifier: Programming Language :: Python :: 3.6
Classifier: Programming Language :: Python :: 3.7
Classifier: Programming Language :: Python :: 3.8
Project-URL: Repository, https://github.com/eganjs/oddysey
